{
   "data":[
      {
         "id":1,
         "title":"rerum qui iusto quia repellendus modi",
         "slug":"rerum-qui-iusto-quia-repellendus-modi-1",
         "body":"Excepturi ea quia vitae quibusdam. Eos consequuntur mollitia dolor officia. Ratione repellendus dolorem distinctio veritatis. Possimus quo qui. Quis eos dolorem ratione dolorem sit eius sit quasi. Voluptatibus labore quia vitae.",
         "total_replies":3,
         "user":{
            "id":5,
            "name":"Márcia Pereira",
            "email":"Flix33@bol.com.br",
            "created_at":1583177252501
         },
         "created_at":1582832252501
      },
      {
         "id":2,
         "title":"non autem qui vitae in",
         "slug":"non-autem-qui-vitae-in-2",
         "body":"Quidem aut quod corporis. Pariatur delectus quia non aperiam. Ducimus quam voluptas quod. Dolorum eveniet minima delectus dolor. Quia ipsam ut.",
         "total_replies":4,
         "user":{
            "id":3,
            "name":"Frederico Nogueira",
            "email":"gor99@bol.com.br",
            "created_at":1583147252501
         },
         "created_at":1582847252501
      },
      {
         "id":3,
         "title":"tempore aut aut non nobis fuga molestiae",
         "slug":"tempore-aut-aut-non-nobis-fuga-molestiae-3",
         "body":"Repellendus occaecati doloremque quia qui vitae officiis. Sunt corrupti in aspernatur itaque et saepe et vel in. Tempore autem aut enim et facilis porro expedita id. Soluta distinctio et. Exercitationem amet aut ab voluptatem. Doloremque sunt consequuntur a fuga aspernatur consequatur.",
         "total_replies":4,
         "user":{
            "id":2,
            "name":"Frederico Saraiva",
            "email":"gor_Oliveira79@hotmail.com",
            "created_at":1583132252501
         },
         "created_at":1582862252502
      },
      {
         "id":4,
         "title":"in explicabo explicabo vel necessitatibus et",
         "slug":"in-explicabo-explicabo-vel-necessitatibus-et-4",
         "body":"Architecto ratione dolorem quia modi id aliquam totam. Laborum modi ut quibusdam est voluptas enim accusantium nisi ut. Est et voluptatem alias. Mollitia aut et voluptates. Error qui voluptatem fuga velit sint pariatur. Aliquam aut consectetur omnis ducimus nobis.",
         "total_replies":3,
         "user":{
            "id":1,
            "name":"Víctor Nogueira Filho",
            "email":"Oflia10@live.com",
            "created_at":1583117252501
         },
         "created_at":1582877252502
      },
      {
         "id":5,
         "title":"nisi consequatur placeat",
         "slug":"nisi-consequatur-placeat-5",
         "body":"Praesentium aspernatur magnam quae architecto repudiandae veritatis mollitia earum. Accusamus veritatis ea aut aspernatur iusto. Perferendis consequuntur accusantium quia id dolores dolores accusamus. Aliquid qui saepe ut excepturi aliquid nisi itaque et pariatur. Ipsam dolorum voluptatem.",
         "total_replies":5,
         "user":{
            "id":5,
            "name":"Márcia Pereira",
            "email":"Flix33@bol.com.br",
            "created_at":1583177252501
         },
         "created_at":1582892252502
      },
      {
         "id":6,
         "title":"ratione eligendi molestias soluta numquam",
         "slug":"ratione-eligendi-molestias-soluta-numquam-6",
         "body":"Officia odit provident eos dolorem. Sit ad quia tempora soluta cum deserunt corrupti eos. Doloribus et itaque vel tempore ea quod natus. Eos corrupti itaque tempore ducimus rerum autem. Distinctio itaque eaque ut aut sed est velit et. Enim et qui voluptatibus eveniet aspernatur molestias consequatur adipisci.",
         "total_replies":3,
         "user":{
            "id":1,
            "name":"Víctor Nogueira Filho",
            "email":"Oflia10@live.com",
            "created_at":1583117252501
         },
         "created_at":1582907252502
      },
      {
         "id":7,
         "title":"sint consectetur illo nobis et",
         "slug":"sint-consectetur-illo-nobis-et-7",
         "body":"Cupiditate deserunt temporibus aut qui deserunt minus eum. Quia nihil atque tempore molestiae fugit perspiciatis et dolor ut. Beatae cumque nihil consequuntur error veritatis et numquam possimus nihil. Doloremque aut inventore id. Unde est eos ratione nisi est enim fugit labore culpa.",
         "total_replies":0,
         "user":{
            "id":6,
            "name":"Srta. Bruna Batista",
            "email":"Slvia.Nogueira@bol.com.br",
            "created_at":1583192252501
         },
         "created_at":1582922252502
      },
      {
         "id":8,
         "title":"blanditiis quidem non temporibus",
         "slug":"blanditiis-quidem-non-temporibus-8",
         "body":"Esse rerum nisi recusandae dolores. Earum placeat consequatur magni accusamus voluptatem eum delectus rerum beatae. Provident aspernatur quis eum ea dolores ut cumque. Autem voluptate voluptates accusantium laborum voluptas veniam deleniti ut sint. Aliquid fugiat repudiandae adipisci aut iure.",
         "total_replies":5,
         "user":{
            "id":5,
            "name":"Márcia Pereira",
            "email":"Flix33@bol.com.br",
            "created_at":1583177252501
         },
         "created_at":1582937252502
      },
      {
         "id":9,
         "title":"et sit voluptas",
         "slug":"et-sit-voluptas-9",
         "body":"Possimus beatae architecto consectetur voluptatibus reprehenderit cumque et. Et numquam autem ut cumque et rerum debitis et. Sit voluptas nemo sunt maxime dignissimos. Accusantium voluptas aperiam nostrum. Inventore quis et tempora. Laborum error rerum debitis optio optio recusandae.",
         "total_replies":3,
         "user":{
            "id":6,
            "name":"Srta. Bruna Batista",
            "email":"Slvia.Nogueira@bol.com.br",
            "created_at":1583192252501
         },
         "created_at":1582952252502
      },
      {
         "id":10,
         "title":"laborum aut et",
         "slug":"laborum-aut-et-10",
         "body":"Sit totam repellat et doloribus nulla qui qui beatae accusamus. Itaque cum rerum sequi consequatur maxime est. In ipsam earum. Non sed est ut hic omnis. Quibusdam repellat vel adipisci est et autem.",
         "total_replies":4,
         "user":{
            "id":5,
            "name":"Márcia Pereira",
            "email":"Flix33@bol.com.br",
            "created_at":1583177252501
         },
         "created_at":1582967252502
      },
      {
         "id":11,
         "title":"suscipit quia asperiores",
         "slug":"suscipit-quia-asperiores-11",
         "body":"Incidunt consequuntur facilis. Ut et atque porro perferendis. A non iusto beatae atque omnis similique voluptas atque. Sed veniam commodi porro.",
         "total_replies":2,
         "user":{
            "id":6,
            "name":"Srta. Bruna Batista",
            "email":"Slvia.Nogueira@bol.com.br",
            "created_at":1583192252501
         },
         "created_at":1582982252502
      },
      {
         "id":12,
         "title":"sed iusto beatae ipsam aut",
         "slug":"sed-iusto-beatae-ipsam-aut-12",
         "body":"Eligendi ut hic ipsam ut quia aut ullam. Dolores et labore sed unde officia id deserunt aut. Nisi deserunt ad et. Eos sunt debitis ut sapiente qui vitae quo quas et.",
         "total_replies":5,
         "user":{
            "id":2,
            "name":"Frederico Saraiva",
            "email":"gor_Oliveira79@hotmail.com",
            "created_at":1583132252501
         },
         "created_at":1582997252502
      },
      {
         "id":13,
         "title":"est inventore et labore ea ullam",
         "slug":"est-inventore-et-labore-ea-ullam-13",
         "body":"Repudiandae ea eos placeat impedit in vel id esse ut. Nam inventore iusto eligendi non voluptatem. Qui sequi consequatur perferendis. Distinctio sed distinctio sit tenetur odio sed. Excepturi voluptatum ducimus est est perferendis autem ut et aut. Pariatur placeat nam quibusdam sapiente.",
         "total_replies":2,
         "user":{
            "id":3,
            "name":"Frederico Nogueira",
            "email":"gor99@bol.com.br",
            "created_at":1583147252501
         },
         "created_at":1583012252502
      },
      {
         "id":14,
         "title":"ratione ducimus maiores ipsa sit rem sint",
         "slug":"ratione-ducimus-maiores-ipsa-sit-rem-sint-14",
         "body":"Accusamus quia vel repudiandae similique voluptas voluptas et. Dolorum explicabo et nostrum ut. Et numquam et aut quaerat vero. Tenetur ut voluptatem aut quas eum. Culpa quos architecto ut voluptas officiis aspernatur excepturi quod quis. Odit cupiditate praesentium sint suscipit sed dolor.",
         "total_replies":4,
         "user":{
            "id":6,
            "name":"Srta. Bruna Batista",
            "email":"Slvia.Nogueira@bol.com.br",
            "created_at":1583192252501
         },
         "created_at":1583027252502
      },
      {
         "id":15,
         "title":"in numquam veniam consequuntur aut exercitationem",
         "slug":"in-numquam-veniam-consequuntur-aut-exercitationem-15",
         "body":"Vero dolorem harum aliquam dignissimos et molestiae rem. Quasi ut ab repellendus distinctio. Voluptas totam quia ab soluta. Beatae ea dolorem suscipit eos ab.",
         "total_replies":3,
         "user":{
            "id":6,
            "name":"Srta. Bruna Batista",
            "email":"Slvia.Nogueira@bol.com.br",
            "created_at":1583192252501
         },
         "created_at":1583042252502
      },
      {
         "id":16,
         "title":"voluptatem qui sed dolorem impedit recusandae",
         "slug":"voluptatem-qui-sed-dolorem-impedit-recusandae-16",
         "body":"Cumque tempore quo. Numquam corrupti autem impedit molestiae quis earum pariatur veritatis et. Et nobis earum qui voluptatibus amet sit doloremque rerum. Saepe et sit sequi. Molestias accusamus eaque omnis rerum eos. Reiciendis sint fugiat.",
         "total_replies":6,
         "user":{
            "id":5,
            "name":"Márcia Pereira",
            "email":"Flix33@bol.com.br",
            "created_at":1583177252501
         },
         "created_at":1583057252502
      },
      {
         "id":17,
         "title":"praesentium et voluptatem cum incidunt impedit",
         "slug":"praesentium-et-voluptatem-cum-incidunt-impedit-17",
         "body":"Atque iste et. Eveniet magnam et quos tempora nulla qui est ipsa dolore. Est voluptatem quod non. Deserunt impedit possimus nihil.",
         "total_replies":4,
         "user":{
            "id":5,
            "name":"Márcia Pereira",
            "email":"Flix33@bol.com.br",
            "created_at":1583177252501
         },
         "created_at":1583072252502
      },
      {
         "id":18,
         "title":"asperiores velit explicabo molestiae consequatur est expedita",
         "slug":"asperiores-velit-explicabo-molestiae-consequatur-est-expedita-18",
         "body":"Laudantium consequatur libero. Earum nulla odit voluptatibus aut doloremque quia adipisci est aut. Qui iure qui praesentium et. Et aliquid rerum dolor et.",
         "total_replies":3,
         "user":{
            "id":3,
            "name":"Frederico Nogueira",
            "email":"gor99@bol.com.br",
            "created_at":1583147252501
         },
         "created_at":1583087252502
      },
      {
         "id":19,
         "title":"aliquam eligendi quasi",
         "slug":"aliquam-eligendi-quasi-19",
         "body":"Asperiores laborum maiores labore. Atque numquam velit at eius. Magnam modi et velit id cum esse vel impedit. Perspiciatis et quos et. Et sed quia est totam nemo odio et ipsa. Dolor consequatur eaque ut et esse.",
         "total_replies":6,
         "user":{
            "id":4,
            "name":"Sra. Fabrícia Pereira",
            "email":"Joana.Martins57@bol.com.br",
            "created_at":1583162252501
         },
         "created_at":1583102252502
      },
      {
         "id":20,
         "title":"exercitationem nihil fuga doloremque ut mollitia officia",
         "slug":"exercitationem-nihil-fuga-doloremque-ut-mollitia-officia-20",
         "body":"Rerum non ipsum atque distinctio molestiae rerum recusandae. Ut labore ipsum voluptates dignissimos voluptas rerum repudiandae enim pariatur. Expedita cum perferendis enim voluptates dolor laborum ut quas delectus. Vel voluptatem ex in. Molestias aperiam laboriosam ab in quia nulla.",
         "total_replies":3,
         "user":{
            "id":4,
            "name":"Sra. Fabrícia Pereira",
            "email":"Joana.Martins57@bol.com.br",
            "created_at":1583162252501
         },
         "created_at":1583117252502
      },
      {
         "id":21,
         "title":"et odit provident aspernatur eius vel aliquid",
         "slug":"et-odit-provident-aspernatur-eius-vel-aliquid-21",
         "body":"Sit voluptas asperiores illo laborum ullam sed cumque facilis. Et voluptatem sit eaque rem dolorem assumenda impedit consequatur. Nesciunt recusandae sed dolorem cum consequatur fugiat quaerat consectetur accusamus. Nesciunt impedit ducimus voluptas sit et nihil nisi iure porro. Nulla ipsa dignissimos incidunt quia molestias ut sed. Sint praesentium molestiae perferendis omnis vel necessitatibus recusandae aut.",
         "total_replies":6,
         "user":{
            "id":4,
            "name":"Sra. Fabrícia Pereira",
            "email":"Joana.Martins57@bol.com.br",
            "created_at":1583162252501
         },
         "created_at":1583132252503
      },
      {
         "id":22,
         "title":"dolor in et enim voluptatum",
         "slug":"dolor-in-et-enim-voluptatum-22",
         "body":"Aspernatur expedita dolores dolor ducimus tenetur omnis quas nulla. Reprehenderit hic accusamus cupiditate vitae praesentium veniam perspiciatis aut. Tenetur ut dolorem adipisci tempora est rem expedita expedita. Neque quibusdam maxime ut.",
         "total_replies":9,
         "user":{
            "id":2,
            "name":"Frederico Saraiva",
            "email":"gor_Oliveira79@hotmail.com",
            "created_at":1583132252501
         },
         "created_at":1583147252503
      },
      {
         "id":23,
         "title":"dolor rerum dicta ipsam est totam expedita",
         "slug":"dolor-rerum-dicta-ipsam-est-totam-expedita-23",
         "body":"Nobis voluptate sint eos voluptatibus magni tempore voluptate iure minima. Nostrum necessitatibus unde quae. Eaque est magnam accusantium qui voluptatem modi odit similique sed. Natus accusamus ducimus fugit ex.",
         "total_replies":3,
         "user":{
            "id":3,
            "name":"Frederico Nogueira",
            "email":"gor99@bol.com.br",
            "created_at":1583147252501
         },
         "created_at":1583162252503
      },
      {
         "id":24,
         "title":"est odit molestias ut aut ipsam",
         "slug":"est-odit-molestias-ut-aut-ipsam-24",
         "body":"Expedita aut aut suscipit hic. Dignissimos soluta voluptas ducimus eum. Dolores iure excepturi nemo ex rerum. Incidunt natus consequuntur quis dicta omnis explicabo et.",
         "total_replies":4,
         "user":{
            "id":1,
            "name":"Víctor Nogueira Filho",
            "email":"Oflia10@live.com",
            "created_at":1583117252501
         },
         "created_at":1583177252503
      },
      {
         "id":25,
         "title":"vero et nam",
         "slug":"vero-et-nam-25",
         "body":"Adipisci ex debitis. Itaque vero consequatur autem atque eveniet. Officia aut dolorem dolor autem quo voluptates qui ducimus.",
         "total_replies":2,
         "user":{
            "id":4,
            "name":"Sra. Fabrícia Pereira",
            "email":"Joana.Martins57@bol.com.br",
            "created_at":1583162252501
         },
         "created_at":1583192252503
      },
      {
         "id":26,
         "title":"id corporis et facilis commodi doloribus omnis",
         "slug":"id-corporis-et-facilis-commodi-doloribus-omnis-26",
         "body":"Sed ullam illo aut voluptatum non. Aliquam facere quae consequatur hic fuga et. Exercitationem voluptas qui et vel aspernatur voluptate ipsam hic provident.",
         "total_replies":4,
         "user":{
            "id":5,
            "name":"Márcia Pereira",
            "email":"Flix33@bol.com.br",
            "created_at":1583177252501
         },
         "created_at":1583207252503
      },
      {
         "id":27,
         "title":"tempora labore nobis facere",
         "slug":"tempora-labore-nobis-facere-27",
         "body":"Tenetur similique repudiandae natus. Delectus accusantium ratione cumque non sed iure labore tenetur ut. Doloremque laudantium id ut voluptatem. Non eos quasi enim distinctio sit. Animi optio adipisci quos sed optio sed et.",
         "total_replies":0,
         "user":{
            "id":5,
            "name":"Márcia Pereira",
            "email":"Flix33@bol.com.br",
            "created_at":1583177252501
         },
         "created_at":1583222252503
      }
   ]
}